Metadata-Version: 2.1
Name: testing-cython
Version: 0.1.0
Summary: Testing Cython
Author: William Rosenbaum
